README.md
setup.py
electricity/__init__.py
electricity/tariffs.py
python_electricity.egg-info/PKG-INFO
python_electricity.egg-info/SOURCES.txt
python_electricity.egg-info/dependency_links.txt
python_electricity.egg-info/top_level.txt
tests/__init__.py
tests/test_pt.py