Metadata-Version: 2.1
Name: python-electricity
Version: 0.0.5
Summary: Determine Electricity Tariff Periods in Python
Home-page: https://github.com/dgomes/python-electricity
Author: dgomes
Author-email: diogogomes@gmail.com
Maintainer: dgomes
Maintainer-email: diogogomes@gmail.com
License: MIT
Platform: any
Classifier: Development Status :: 4 - Beta
Classifier: Intended Audience :: Developers
Classifier: License :: OSI Approved :: MIT License
Classifier: Operating System :: OS Independent
Classifier: Programming Language :: Python
Classifier: Programming Language :: Python :: 3.5
Classifier: Programming Language :: Python :: 3.6
Classifier: Programming Language :: Python :: Implementation :: CPython
Classifier: Programming Language :: Python :: Implementation :: PyPy
Classifier: Topic :: Office/Business :: Scheduling
Classifier: Topic :: Software Development :: Libraries :: Python Modules
Classifier: Topic :: Software Development :: Localization
